{
    "base": "EUR",
    "date": "1999-07-27",
    "rates": {
        "AUD": 1.648,
        "CAD": 1.6038,
        "CHF": 1.6,
        "CYP": 0.57874,
        "CZK": 36.695,
        "DKK": 7.4443,
        "EEK": 15.6466,
        "GBP": 0.668,
        "HKD": 8.2482,
        "HUF": 252.82,
        "ISK": 77.9,
        "JPY": 124.27,
        "KRW": 1279.08,
        "LTL": 4.2523,
        "LVL": 0.6325,
        "MTL": 0.4271,
        "NOK": 8.3275,
        "NZD": 2.0292,
        "PLN": 4.0547,
        "ROL": 16950.0,
        "SEK": 8.8055,
        "SGD": 1.7939,
        "SIT": 197.0811,
        "SKK": 44.722,
        "TRL": 455314.0,
        "USD": 1.0627,
        "ZAR": 6.5186
    }
}
