{
    "base": "EUR",
    "date": "2000-04-05",
    "rates": {
        "AUD": 1.5954,
        "CAD": 1.4078,
        "CHF": 1.5732,
        "CYP": 0.57521,
        "CZK": 36.283,
        "DKK": 7.4483,
        "EEK": 15.6466,
        "GBP": 0.6088,
        "HKD": 7.5251,
        "HUF": 258.91,
        "ISK": 70.75,
        "JPY": 101.71,
        "KRW": 1077.54,
        "LTL": 3.8665,
        "LVL": 0.5714,
        "MTL": 0.4091,
        "NOK": 8.157,
        "NZD": 1.9321,
        "PLN": 4.0707,
        "ROL": 18887.0,
        "SEK": 8.329,
        "SGD": 1.6586,
        "SIT": 203.3895,
        "SKK": 41.665,
        "TRL": 567142.0,
        "USD": 0.9673,
        "ZAR": 6.3808
    }
}
