{
    "base": "EUR",
    "date": "2000-08-09",
    "rates": {
        "AUD": 1.5503,
        "BGN": 1.9461,
        "CAD": 1.3351,
        "CHF": 1.5443,
        "CYP": 0.57241,
        "CZK": 35.297,
        "DKK": 7.4568,
        "EEK": 15.6466,
        "GBP": 0.5978,
        "HKD": 6.9985,
        "HUF": 260.68,
        "ISK": 72.13,
        "JPY": 96.81,
        "KRW": 1000.37,
        "LTL": 3.5904,
        "LVL": 0.5447,
        "MTL": 0.3995,
        "NOK": 8.067,
        "NZD": 1.9855,
        "PLN": 3.9174,
        "ROL": 19884.0,
        "SEK": 8.3125,
        "SGD": 1.5457,
        "SIT": 208.5574,
        "SKK": 42.45,
        "TRL": 579904.0,
        "USD": 0.8973,
        "ZAR": 6.2722
    }
}
