{
    "base": "EUR",
    "date": "2001-12-12",
    "rates": {
        "AUD": 1.7235,
        "BGN": 1.9465,
        "CAD": 1.4005,
        "CHF": 1.4739,
        "CYP": 0.57478,
        "CZK": 32.705,
        "DKK": 7.449,
        "EEK": 15.6466,
        "GBP": 0.6207,
        "HKD": 6.9714,
        "HUF": 247.14,
        "ISK": 93.32,
        "JPY": 112.6,
        "KRW": 1136.02,
        "LTL": 3.5745,
        "LVL": 0.559,
        "MTL": 0.4026,
        "NOK": 8.0065,
        "NZD": 2.1242,
        "PLN": 3.6271,
        "ROL": 28300.0,
        "SEK": 9.3833,
        "SGD": 1.6361,
        "SIT": 219.9897,
        "SKK": 43.271,
        "TRL": 1275000.0,
        "USD": 0.8938,
        "ZAR": 9.9972
    }
}
