{
    "base": "EUR",
    "date": "2002-12-24",
    "rates": {
        "AUD": 1.8262,
        "BGN": 1.9516,
        "CAD": 1.5976,
        "CHF": 1.4538,
        "CYP": 0.57248,
        "CZK": 31.253,
        "DKK": 7.4261,
        "EEK": 15.6466,
        "GBP": 0.6467,
        "HKD": 8.0295,
        "HUF": 235.61,
        "ISK": 84.69,
        "JPY": 123.78,
        "KRW": 1236.24,
        "LTL": 3.4521,
        "LVL": 0.6067,
        "MTL": 0.417,
        "NOK": 7.2763,
        "NZD": 1.994,
        "PLN": 3.9793,
        "ROL": 34373.0,
        "SEK": 9.1326,
        "SGD": 1.7922,
        "SIT": 230.035,
        "SKK": 41.79,
        "TRL": 1731000.0,
        "USD": 1.0296,
        "ZAR": 9.0892
    }
}
