{
    "base": "EUR",
    "date": "2003-04-16",
    "rates": {
        "AUD": 1.7724,
        "BGN": 1.9467,
        "CAD": 1.5681,
        "CHF": 1.5021,
        "CYP": 0.58672,
        "CZK": 31.583,
        "DKK": 7.425,
        "EEK": 15.6466,
        "GBP": 0.6877,
        "HKD": 8.4516,
        "HUF": 245.65,
        "ISK": 82.98,
        "JPY": 130.39,
        "KRW": 1314.41,
        "LTL": 3.4535,
        "LVL": 0.628,
        "MTL": 0.4241,
        "NOK": 7.839,
        "NZD": 1.9445,
        "PLN": 4.2852,
        "ROL": 36670.0,
        "SEK": 9.1572,
        "SGD": 1.9254,
        "SIT": 232.4355,
        "SKK": 40.992,
        "TRL": 1748000.0,
        "USD": 1.0836,
        "ZAR": 8.3166
    }
}
