{
    "base": "EUR",
    "date": "2004-04-23",
    "rates": {
        "AUD": 1.6226,
        "BGN": 1.9463,
        "CAD": 1.6105,
        "CHF": 1.5598,
        "CYP": 0.5865,
        "CZK": 32.315,
        "DKK": 7.442,
        "EEK": 15.6466,
        "GBP": 0.66985,
        "HKD": 9.2695,
        "HUF": 250.32,
        "ISK": 87.41,
        "JPY": 129.55,
        "KRW": 1376.82,
        "LTL": 3.4527,
        "LVL": 0.6489,
        "MTL": 0.4253,
        "NOK": 8.238,
        "NZD": 1.8893,
        "PLN": 4.7602,
        "ROL": 40465.0,
        "SEK": 9.1375,
        "SGD": 2.0128,
        "SIT": 238.46,
        "SKK": 40.115,
        "TRL": 1644150.0,
        "USD": 1.1885,
        "ZAR": 8.0102
    }
}
