{
    "base": "EUR",
    "date": "2004-05-28",
    "rates": {
        "AUD": 1.7164,
        "BGN": 1.9471,
        "CAD": 1.6685,
        "CHF": 1.5304,
        "CYP": 0.5845,
        "CZK": 31.77,
        "DKK": 7.438,
        "EEK": 15.6466,
        "GBP": 0.6673,
        "HKD": 9.5447,
        "HUF": 251.2,
        "ISK": 87.72,
        "JPY": 135.77,
        "KRW": 1426.6,
        "LTL": 3.4526,
        "LVL": 0.6604,
        "MTL": 0.4261,
        "NOK": 8.212,
        "NZD": 1.9419,
        "PLN": 4.6453,
        "ROL": 40807.0,
        "SEK": 9.115,
        "SGD": 2.0863,
        "SIT": 238.92,
        "SKK": 40.06,
        "TRL": 1824700.0,
        "USD": 1.2246,
        "ZAR": 7.9739
    }
}
