{
    "base": "EUR",
    "date": "2004-03-22",
    "rates": {
        "AUD": 1.643,
        "BGN": 1.9465,
        "CAD": 1.6407,
        "CHF": 1.5574,
        "CYP": 0.58606,
        "CZK": 33.171,
        "DKK": 7.4469,
        "EEK": 15.6466,
        "GBP": 0.66945,
        "HKD": 9.6263,
        "HUF": 253.2,
        "ISK": 87.6,
        "JPY": 132.17,
        "KRW": 1433.57,
        "LTL": 3.4529,
        "LVL": 0.6606,
        "MTL": 0.4266,
        "NOK": 8.429,
        "NZD": 1.8659,
        "PLN": 4.7318,
        "ROL": 40083.0,
        "SEK": 9.2185,
        "SGD": 2.0881,
        "SIT": 238.03,
        "SKK": 40.255,
        "TRL": 1630333.0,
        "USD": 1.2353,
        "ZAR": 8.1701
    }
}
