{
    "base": "EUR",
    "date": "2004-12-20",
    "rates": {
        "AUD": 1.7516,
        "BGN": 1.9559,
        "CAD": 1.6428,
        "CHF": 1.5382,
        "CYP": 0.5788,
        "CZK": 30.46,
        "DKK": 7.4329,
        "EEK": 15.6466,
        "GBP": 0.6874,
        "HKD": 10.4076,
        "HUF": 244.93,
        "ISK": 83.9,
        "JPY": 139.44,
        "KRW": 1415.66,
        "LTL": 3.4528,
        "LVL": 0.688,
        "MTL": 0.4315,
        "NOK": 8.229,
        "NZD": 1.8672,
        "PLN": 4.1223,
        "ROL": 38672.0,
        "SEK": 8.963,
        "SGD": 2.1994,
        "SIT": 239.78,
        "SKK": 38.545,
        "TRL": 1855600.0,
        "USD": 1.3378,
        "ZAR": 7.6633
    }
}
