{
    "base": "EUR",
    "date": "2005-11-03",
    "rates": {
        "AUD": 1.6222,
        "BGN": 1.9559,
        "CAD": 1.4164,
        "CHF": 1.5428,
        "CNY": 9.7341,
        "CYP": 0.5737,
        "CZK": 29.446,
        "DKK": 7.464,
        "EEK": 15.6466,
        "GBP": 0.67825,
        "HKD": 9.3348,
        "HRK": 7.3928,
        "HUF": 248.23,
        "IDR": 12102.41,
        "ISK": 71.98,
        "JPY": 140.76,
        "KRW": 1256.48,
        "LTL": 3.4528,
        "LVL": 0.6965,
        "MTL": 0.4293,
        "MYR": 4.5473,
        "NOK": 7.8075,
        "NZD": 1.7351,
        "PHP": 65.744,
        "PLN": 3.9609,
        "RON": 3.6586,
        "RUB": 34.383,
        "SEK": 9.6148,
        "SGD": 2.0425,
        "SIT": 239.5,
        "SKK": 38.93,
        "THB": 49.163,
        "TRY": 1.6245,
        "USD": 1.2041,
        "ZAR": 7.9603
    }
}
