{
    "base": "EUR",
    "date": "2006-11-22",
    "rates": {
        "AUD": 1.6669,
        "BGN": 1.9558,
        "CAD": 1.4686,
        "CHF": 1.5884,
        "CNY": 10.1345,
        "CYP": 0.5778,
        "CZK": 27.942,
        "DKK": 7.4554,
        "EEK": 15.6466,
        "GBP": 0.6749,
        "HKD": 10.0337,
        "HRK": 7.3688,
        "HUF": 257.45,
        "IDR": 11770.07,
        "ISK": 92.6,
        "JPY": 150.75,
        "KRW": 1203.55,
        "LTL": 3.4528,
        "LVL": 0.6974,
        "MTL": 0.4293,
        "MYR": 4.6969,
        "NOK": 8.252,
        "NZD": 1.9249,
        "PHP": 64.095,
        "PLN": 3.8006,
        "RON": 3.4983,
        "RUB": 34.283,
        "SEK": 9.0965,
        "SGD": 2.0045,
        "SIT": 239.66,
        "SKK": 35.656,
        "THB": 47.133,
        "TRY": 1.894,
        "USD": 1.2886,
        "ZAR": 9.2537
    }
}
