{
    "base": "EUR",
    "date": "2006-09-04",
    "rates": {
        "AUD": 1.668,
        "BGN": 1.9558,
        "CAD": 1.4219,
        "CHF": 1.5812,
        "CNY": 10.2026,
        "CYP": 0.5763,
        "CZK": 28.19,
        "DKK": 7.4606,
        "EEK": 15.6466,
        "GBP": 0.67475,
        "HKD": 9.9959,
        "HRK": 7.3485,
        "HUF": 277.22,
        "IDR": 11672.83,
        "ISK": 88.86,
        "JPY": 149.22,
        "KRW": 1231.09,
        "LTL": 3.4528,
        "LVL": 0.6961,
        "MTL": 0.4293,
        "MYR": 4.7025,
        "NOK": 8.126,
        "NZD": 1.9691,
        "PHP": 64.838,
        "PLN": 3.9717,
        "RON": 3.527,
        "RUB": 34.332,
        "SEK": 9.3177,
        "SGD": 2.0154,
        "SIT": 239.61,
        "SKK": 37.67,
        "THB": 48.002,
        "TRY": 1.872,
        "USD": 1.2852,
        "ZAR": 9.2313
    }
}
