{
    "base": "EUR",
    "date": "2007-08-30",
    "rates": {
        "AUD": 1.6677,
        "BGN": 1.9558,
        "CAD": 1.4454,
        "CHF": 1.6402,
        "CNY": 10.2633,
        "CYP": 0.5842,
        "CZK": 27.594,
        "DKK": 7.4472,
        "EEK": 15.6466,
        "GBP": 0.678,
        "HKD": 10.6142,
        "HRK": 7.3212,
        "HUF": 255.44,
        "IDR": 12820.62,
        "ISK": 86.71,
        "JPY": 157.33,
        "KRW": 1280.02,
        "LTL": 3.4528,
        "LVL": 0.6974,
        "MTL": 0.4293,
        "MYR": 4.7689,
        "NOK": 7.959,
        "NZD": 1.9404,
        "PHP": 63.695,
        "PLN": 3.8271,
        "RON": 3.2616,
        "RUB": 34.928,
        "SEK": 9.3832,
        "SGD": 2.0761,
        "SKK": 33.74,
        "THB": 44.344,
        "TRY": 1.7943,
        "USD": 1.361,
        "ZAR": 9.7932
    }
}
