{
    "base": "EUR",
    "date": "2007-11-12",
    "rates": {
        "AUD": 1.6516,
        "BGN": 1.9558,
        "CAD": 1.3956,
        "CHF": 1.6403,
        "CNY": 10.8064,
        "CYP": 0.5842,
        "CZK": 26.645,
        "DKK": 7.4525,
        "EEK": 15.6466,
        "GBP": 0.70445,
        "HKD": 11.3519,
        "HRK": 7.344,
        "HUF": 254.5,
        "IDR": 13368.94,
        "ISK": 88.74,
        "JPY": 159.55,
        "KRW": 1329.02,
        "LTL": 3.4528,
        "LVL": 0.7024,
        "MTL": 0.4293,
        "MYR": 4.8657,
        "NOK": 7.874,
        "NZD": 1.9524,
        "PHP": 62.602,
        "PLN": 3.6437,
        "RON": 3.4451,
        "RUB": 35.801,
        "SEK": 9.3214,
        "SGD": 2.1113,
        "SKK": 33.0,
        "THB": 46.079,
        "TRY": 1.766,
        "USD": 1.4579,
        "ZAR": 9.8305
    }
}
