{
    "base": "EUR",
    "date": "2007-11-15",
    "rates": {
        "AUD": 1.6425,
        "BGN": 1.9558,
        "CAD": 1.4273,
        "CHF": 1.6454,
        "CNY": 10.8662,
        "CYP": 0.5842,
        "CZK": 26.624,
        "DKK": 7.4527,
        "EEK": 15.6466,
        "GBP": 0.71485,
        "HKD": 11.3961,
        "HRK": 7.3525,
        "HUF": 254.42,
        "IDR": 13631.84,
        "ISK": 88.44,
        "JPY": 161.98,
        "KRW": 1340.35,
        "LTL": 3.4528,
        "LVL": 0.7001,
        "MTL": 0.4293,
        "MYR": 4.9355,
        "NOK": 7.9935,
        "NZD": 1.9329,
        "PHP": 63.24,
        "PLN": 3.6672,
        "RON": 3.458,
        "RUB": 35.865,
        "SEK": 9.248,
        "SGD": 2.1255,
        "SKK": 33.09,
        "THB": 46.21,
        "TRY": 1.732,
        "USD": 1.4639,
        "ZAR": 9.7941
    }
}
