{
    "base": "EUR",
    "date": "2007-07-26",
    "rates": {
        "AUD": 1.5561,
        "BGN": 1.9558,
        "CAD": 1.4396,
        "CHF": 1.6607,
        "CNY": 10.3814,
        "CYP": 0.5842,
        "CZK": 28.124,
        "DKK": 7.4413,
        "EEK": 15.6466,
        "GBP": 0.6708,
        "HKD": 10.7372,
        "HRK": 7.2905,
        "HUF": 249.04,
        "IDR": 12539.16,
        "ISK": 82.79,
        "JPY": 164.52,
        "KRW": 1260.02,
        "LTL": 3.4528,
        "LVL": 0.6969,
        "MTL": 0.4293,
        "MYR": 4.719,
        "NOK": 7.976,
        "NZD": 1.7262,
        "PHP": 62.174,
        "PLN": 3.806,
        "RON": 3.1436,
        "RUB": 34.975,
        "SEK": 9.2266,
        "SGD": 2.079,
        "SKK": 33.353,
        "THB": 40.651,
        "TRY": 1.7518,
        "USD": 1.3722,
        "ZAR": 9.5685
    }
}
