{
    "base": "EUR",
    "date": "2008-01-08",
    "rates": {
        "AUD": 1.6712,
        "BGN": 1.9558,
        "BRL": 2.5796,
        "CAD": 1.4724,
        "CHF": 1.6428,
        "CNY": 10.6822,
        "CZK": 26.125,
        "DKK": 7.4485,
        "EEK": 15.6466,
        "GBP": 0.7445,
        "HKD": 11.4727,
        "HRK": 7.3476,
        "HUF": 254.45,
        "IDR": 13896.96,
        "ISK": 91.38,
        "JPY": 161.23,
        "KRW": 1381.24,
        "LTL": 3.4528,
        "LVL": 0.6977,
        "MXN": 15.9902,
        "MYR": 4.81,
        "NOK": 7.8895,
        "NZD": 1.9084,
        "PHP": 59.945,
        "PLN": 3.5944,
        "RON": 3.5914,
        "RUB": 35.98,
        "SEK": 9.3806,
        "SGD": 2.1047,
        "SKK": 33.413,
        "THB": 43.772,
        "TRY": 1.7055,
        "USD": 1.4705,
        "ZAR": 10.109
    }
}
