{
    "base": "EUR",
    "date": "2009-07-02",
    "rates": {
        "AUD": 1.7525,
        "BGN": 1.9558,
        "BRL": 2.7222,
        "CAD": 1.6201,
        "CHF": 1.5235,
        "CNY": 9.5974,
        "CZK": 25.755,
        "DKK": 7.446,
        "EEK": 15.6466,
        "GBP": 0.8573,
        "HKD": 10.8879,
        "HRK": 7.2992,
        "HUF": 268.45,
        "IDR": 14374.42,
        "INR": 67.358,
        "JPY": 135.95,
        "KRW": 1783.8,
        "LTL": 3.4528,
        "LVL": 0.7005,
        "MXN": 18.4393,
        "MYR": 4.9452,
        "NOK": 8.9375,
        "NZD": 2.2168,
        "PHP": 67.569,
        "PLN": 4.3543,
        "RON": 4.2062,
        "RUB": 43.8009,
        "SEK": 10.84,
        "SGD": 2.0377,
        "THB": 47.9,
        "TRY": 2.1489,
        "USD": 1.4049,
        "ZAR": 10.9708
    }
}
