{
    "base": "EUR",
    "date": "2009-03-12",
    "rates": {
        "AUD": 1.9785,
        "BGN": 1.9558,
        "BRL": 2.9724,
        "CAD": 1.646,
        "CHF": 1.5225,
        "CNY": 8.7414,
        "CZK": 27.015,
        "DKK": 7.4526,
        "EEK": 15.6466,
        "GBP": 0.9308,
        "HKD": 9.912,
        "HRK": 7.4404,
        "HUF": 302.25,
        "IDR": 15427.87,
        "INR": 66.326,
        "JPY": 124.3,
        "KRW": 1916.3,
        "LTL": 3.4528,
        "LVL": 0.707,
        "MXN": 19.2753,
        "MYR": 4.7198,
        "NOK": 8.892,
        "NZD": 2.4984,
        "PHP": 62.06,
        "PLN": 4.604,
        "RON": 4.2853,
        "RUB": 44.9973,
        "SEK": 11.2122,
        "SGD": 1.9553,
        "THB": 45.98,
        "TRY": 2.2284,
        "USD": 1.2782,
        "ZAR": 12.9469
    }
}
