{
    "base": "EUR",
    "date": "2009-02-17",
    "rates": {
        "AUD": 1.975,
        "BGN": 1.9558,
        "BRL": 2.9121,
        "CAD": 1.5959,
        "CHF": 1.4813,
        "CNY": 8.641,
        "CZK": 29.49,
        "DKK": 7.452,
        "EEK": 15.6466,
        "GBP": 0.8851,
        "HKD": 9.7966,
        "HRK": 7.4736,
        "HUF": 307.15,
        "IDR": 15539.82,
        "INR": 62.456,
        "JPY": 116.2,
        "KRW": 1850.88,
        "LTL": 3.4528,
        "LVL": 0.7076,
        "MXN": 18.4469,
        "MYR": 4.5994,
        "NOK": 8.794,
        "NZD": 2.479,
        "PHP": 60.45,
        "PLN": 4.8795,
        "RON": 4.305,
        "RUB": 45.7558,
        "SEK": 10.978,
        "SGD": 1.9275,
        "THB": 44.554,
        "TRY": 2.1209,
        "USD": 1.2634,
        "ZAR": 12.8734
    }
}
