{
    "base": "EUR",
    "date": "2009-09-25",
    "rates": {
        "AUD": 1.6952,
        "BGN": 1.9558,
        "BRL": 2.6382,
        "CAD": 1.6035,
        "CHF": 1.5118,
        "CNY": 10.017,
        "CZK": 25.18,
        "DKK": 7.442,
        "EEK": 15.6466,
        "GBP": 0.91875,
        "HKD": 11.3696,
        "HRK": 7.295,
        "HUF": 270.0,
        "IDR": 14164.36,
        "INR": 70.328,
        "JPY": 132.59,
        "KRW": 1740.22,
        "LTL": 3.4528,
        "LVL": 0.7069,
        "MXN": 19.7957,
        "MYR": 5.092,
        "NOK": 8.502,
        "NZD": 2.0462,
        "PHP": 69.412,
        "PLN": 4.196,
        "RON": 4.2008,
        "RUB": 44.1365,
        "SEK": 10.1538,
        "SGD": 2.0787,
        "THB": 49.284,
        "TRY": 2.1779,
        "USD": 1.467,
        "ZAR": 10.9049
    }
}
