{
    "base": "EUR",
    "date": "2011-10-11",
    "rates": {
        "AUD": 1.3684,
        "BGN": 1.9558,
        "BRL": 2.412,
        "CAD": 1.3988,
        "CHF": 1.238,
        "CNY": 8.6758,
        "CZK": 24.779,
        "DKK": 7.4435,
        "GBP": 0.8702,
        "HKD": 10.5882,
        "HRK": 7.472,
        "HUF": 295.05,
        "IDR": 12159.79,
        "ILS": 5.0345,
        "INR": 67.117,
        "JPY": 104.26,
        "KRW": 1593.88,
        "LTL": 3.4528,
        "LVL": 0.7056,
        "MXN": 18.1467,
        "MYR": 4.2746,
        "NOK": 7.781,
        "NZD": 1.7462,
        "PHP": 59.111,
        "PLN": 4.3284,
        "RON": 4.329,
        "RUB": 42.928,
        "SEK": 9.1202,
        "SGD": 1.7485,
        "THB": 42.1,
        "TRY": 2.5075,
        "USD": 1.3607,
        "ZAR": 10.8185
    }
}
