{
    "base": "EUR",
    "date": "2011-03-01",
    "rates": {
        "AUD": 1.3572,
        "BGN": 1.9558,
        "BRL": 2.2991,
        "CAD": 1.3408,
        "CHF": 1.2849,
        "CNY": 9.0816,
        "CZK": 24.355,
        "DKK": 7.4559,
        "GBP": 0.8494,
        "HKD": 10.7668,
        "HRK": 7.4222,
        "HUF": 272.64,
        "IDR": 12163.51,
        "ILS": 5.0152,
        "INR": 62.143,
        "JPY": 113.39,
        "KRW": 1550.25,
        "LTL": 3.4528,
        "LVL": 0.7045,
        "MXN": 16.7175,
        "MYR": 4.1897,
        "NOK": 7.712,
        "NZD": 1.8397,
        "PHP": 60.026,
        "PLN": 3.9725,
        "RON": 4.212,
        "RUB": 39.675,
        "SEK": 8.709,
        "SGD": 1.7562,
        "THB": 42.235,
        "TRY": 2.2214,
        "USD": 1.3825,
        "ZAR": 9.6111
    }
}
