{
    "base": "EUR",
    "date": "2012-08-10",
    "rates": {
        "AUD": 1.1661,
        "BGN": 1.9558,
        "BRL": 2.4772,
        "CAD": 1.2192,
        "CHF": 1.2009,
        "CNY": 7.7989,
        "CZK": 25.205,
        "DKK": 7.4427,
        "GBP": 0.7861,
        "HKD": 9.5121,
        "HRK": 7.4865,
        "HUF": 278.9,
        "IDR": 11632.35,
        "ILS": 4.9051,
        "INR": 67.79,
        "JPY": 96.12,
        "KRW": 1386.66,
        "LTL": 3.4528,
        "LVL": 0.6962,
        "MXN": 16.1368,
        "MYR": 3.8222,
        "NOK": 7.27,
        "NZD": 1.5162,
        "PHP": 51.261,
        "PLN": 4.0961,
        "RON": 4.5345,
        "RUB": 39.144,
        "SEK": 8.2077,
        "SGD": 1.5296,
        "THB": 38.589,
        "TRY": 2.1942,
        "USD": 1.2262,
        "ZAR": 9.9772
    }
}
