{
    "base": "EUR",
    "date": "2012-05-30",
    "rates": {
        "AUD": 1.2729,
        "BGN": 1.9558,
        "BRL": 2.4921,
        "CAD": 1.2784,
        "CHF": 1.201,
        "CNY": 7.892,
        "CZK": 25.658,
        "DKK": 7.4312,
        "GBP": 0.79775,
        "HKD": 9.6551,
        "HRK": 7.5555,
        "HUF": 298.95,
        "IDR": 11976.3,
        "ILS": 4.8268,
        "INR": 69.942,
        "JPY": 98.38,
        "KRW": 1465.19,
        "LTL": 3.4528,
        "LVL": 0.6982,
        "MXN": 17.3868,
        "MYR": 3.9329,
        "NOK": 7.5145,
        "NZD": 1.6402,
        "PHP": 54.116,
        "PLN": 4.3873,
        "RON": 4.4675,
        "RUB": 40.565,
        "SEK": 8.9555,
        "SGD": 1.5948,
        "THB": 39.627,
        "TRY": 2.293,
        "USD": 1.2438,
        "ZAR": 10.5086
    }
}
