{
    "base": "EUR",
    "date": "2013-04-18",
    "rates": {
        "AUD": 1.2633,
        "BGN": 1.9558,
        "BRL": 2.6207,
        "CAD": 1.3362,
        "CHF": 1.2164,
        "CNY": 8.0632,
        "CZK": 25.875,
        "DKK": 7.4553,
        "GBP": 0.8548,
        "HKD": 10.1268,
        "HRK": 7.6147,
        "HUF": 297.97,
        "IDR": 12675.98,
        "ILS": 4.7306,
        "INR": 70.407,
        "JPY": 128.4,
        "KRW": 1461.22,
        "LTL": 3.4528,
        "LVL": 0.7002,
        "MXN": 15.8927,
        "MYR": 3.9579,
        "NOK": 7.587,
        "NZD": 1.5454,
        "PHP": 53.781,
        "PLN": 4.1147,
        "RON": 4.3729,
        "RUB": 41.21,
        "SEK": 8.5008,
        "SGD": 1.6112,
        "THB": 37.452,
        "TRY": 2.3422,
        "USD": 1.3045,
        "ZAR": 11.9538
    }
}
