{
    "base": "EUR",
    "date": "2013-05-29",
    "rates": {
        "AUD": 1.3447,
        "BGN": 1.9558,
        "BRL": 2.6866,
        "CAD": 1.3434,
        "CHF": 1.248,
        "CNY": 7.9384,
        "CZK": 25.899,
        "DKK": 7.4539,
        "GBP": 0.85695,
        "HKD": 10.0557,
        "HRK": 7.5635,
        "HUF": 288.03,
        "IDR": 12695.06,
        "ILS": 4.7879,
        "INR": 72.758,
        "JPY": 130.9,
        "KRW": 1466.93,
        "LTL": 3.4528,
        "LVL": 0.7013,
        "MXN": 16.3671,
        "MYR": 3.9873,
        "NOK": 7.6,
        "NZD": 1.5912,
        "PHP": 54.946,
        "PLN": 4.225,
        "RON": 4.346,
        "RUB": 40.8379,
        "SEK": 8.6082,
        "SGD": 1.6404,
        "THB": 39.089,
        "TRY": 2.4129,
        "USD": 1.2952,
        "ZAR": 12.6714
    }
}
