{
    "base": "EUR",
    "date": "2014-07-25",
    "rates": {
        "AUD": 1.4289,
        "BGN": 1.9558,
        "BRL": 2.9968,
        "CAD": 1.4472,
        "CHF": 1.2152,
        "CNY": 8.3272,
        "CZK": 27.482,
        "DKK": 7.4568,
        "GBP": 0.79115,
        "HKD": 10.416,
        "HRK": 7.633,
        "HUF": 308.06,
        "IDR": 15561.78,
        "ILS": 4.6004,
        "INR": 80.7677,
        "JPY": 136.97,
        "KRW": 1380.11,
        "LTL": 3.4528,
        "MXN": 17.4162,
        "MYR": 4.2655,
        "NOK": 8.3395,
        "NZD": 1.5728,
        "PHP": 58.199,
        "PLN": 4.1435,
        "RON": 4.3973,
        "RUB": 47.1871,
        "SEK": 9.1661,
        "SGD": 1.6682,
        "THB": 42.78,
        "TRY": 2.8145,
        "USD": 1.344,
        "ZAR": 14.1489
    }
}
