{
    "base": "EUR",
    "date": "2016-06-03",
    "rates": {
        "AUD": 1.5397,
        "BGN": 1.9558,
        "BRL": 3.9973,
        "CAD": 1.4594,
        "CHF": 1.105,
        "CNY": 7.3468,
        "CZK": 27.025,
        "DKK": 7.4382,
        "GBP": 0.77285,
        "HKD": 8.6683,
        "HRK": 7.4958,
        "HUF": 312.44,
        "IDR": 15146.02,
        "ILS": 4.3239,
        "INR": 75.011,
        "JPY": 121.47,
        "KRW": 1322.41,
        "MXN": 20.8803,
        "MYR": 4.6261,
        "NOK": 9.2853,
        "NZD": 1.6287,
        "PHP": 51.821,
        "PLN": 4.3861,
        "RON": 4.5188,
        "RUB": 74.9088,
        "SEK": 9.2605,
        "SGD": 1.5351,
        "THB": 39.719,
        "TRY": 3.2902,
        "USD": 1.1154,
        "ZAR": 17.3778
    }
}
