{
    "base": "EUR",
    "date": "2016-08-11",
    "rates": {
        "AUD": 1.446,
        "BGN": 1.9558,
        "BRL": 3.5156,
        "CAD": 1.4559,
        "CHF": 1.0859,
        "CNY": 7.4031,
        "CZK": 27.02,
        "DKK": 7.4386,
        "GBP": 0.86038,
        "HKD": 8.6506,
        "HRK": 7.4952,
        "HUF": 310.26,
        "IDR": 14610.43,
        "ILS": 4.252,
        "INR": 74.5558,
        "JPY": 113.05,
        "KRW": 1226.97,
        "MXN": 20.5527,
        "MYR": 4.4676,
        "NOK": 9.2293,
        "NZD": 1.539,
        "PHP": 52.085,
        "PLN": 4.2604,
        "RON": 4.4601,
        "RUB": 72.3675,
        "SEK": 9.431,
        "SGD": 1.4989,
        "THB": 38.746,
        "TRY": 3.305,
        "USD": 1.1153,
        "ZAR": 14.908
    }
}
