{
    "base": "EUR",
    "date": "2016-03-24",
    "rates": {
        "AUD": 1.4858,
        "BGN": 1.9558,
        "BRL": 4.1316,
        "CAD": 1.4821,
        "CHF": 1.0875,
        "CNY": 7.2662,
        "CZK": 27.064,
        "DKK": 7.4546,
        "GBP": 0.78938,
        "HKD": 8.6548,
        "HRK": 7.5358,
        "HUF": 314.24,
        "IDR": 14781.84,
        "ILS": 4.2753,
        "INR": 74.579,
        "JPY": 125.41,
        "KRW": 1302.21,
        "MXN": 19.7076,
        "MYR": 4.4956,
        "NOK": 9.494,
        "NZD": 1.6645,
        "PHP": 51.766,
        "PLN": 4.2788,
        "RON": 4.4669,
        "RUB": 77.7413,
        "SEK": 9.2688,
        "SGD": 1.5268,
        "THB": 39.407,
        "TRY": 3.211,
        "USD": 1.1154,
        "ZAR": 17.2854
    }
}
