{
    "base": "EUR",
    "date": "2016-12-09",
    "rates": {
        "AUD": 1.4141,
        "BGN": 1.9558,
        "BRL": 3.5815,
        "CAD": 1.3914,
        "CHF": 1.0756,
        "CNY": 7.2931,
        "CZK": 27.027,
        "DKK": 7.4369,
        "GBP": 0.83935,
        "HKD": 8.1934,
        "HRK": 7.5327,
        "HUF": 314.45,
        "IDR": 14072.51,
        "ILS": 4.04,
        "INR": 71.341,
        "JPY": 121.48,
        "KRW": 1237.0,
        "MXN": 21.5825,
        "MYR": 4.6708,
        "NOK": 8.9805,
        "NZD": 1.4745,
        "PHP": 52.615,
        "PLN": 4.4454,
        "RON": 4.4994,
        "RUB": 66.6988,
        "SEK": 9.691,
        "SGD": 1.5079,
        "THB": 37.664,
        "TRY": 3.6707,
        "USD": 1.0559,
        "ZAR": 14.545
    }
}
