{
    "base": "EUR",
    "date": "2017-08-22",
    "rates": {
        "AUD": 1.4887,
        "BGN": 1.9558,
        "BRL": 3.7102,
        "CAD": 1.4806,
        "CHF": 1.1364,
        "CNY": 7.843,
        "CZK": 26.083,
        "DKK": 7.4377,
        "GBP": 0.91713,
        "HKD": 9.2129,
        "HRK": 7.4045,
        "HUF": 303.7,
        "IDR": 15706.05,
        "ILS": 4.2595,
        "INR": 75.4515,
        "JPY": 128.73,
        "KRW": 1335.14,
        "MXN": 20.7907,
        "MYR": 5.0392,
        "NOK": 9.3023,
        "NZD": 1.6165,
        "PHP": 60.33,
        "PLN": 4.2818,
        "RON": 4.5868,
        "RUB": 69.484,
        "SEK": 9.539,
        "SGD": 1.6032,
        "THB": 39.127,
        "TRY": 4.117,
        "USD": 1.1771,
        "ZAR": 15.5407
    }
}
