{
    "base": "EUR",
    "date": "2017-06-20",
    "rates": {
        "AUD": 1.4674,
        "BGN": 1.9558,
        "BRL": 3.6845,
        "CAD": 1.4812,
        "CHF": 1.0854,
        "CNY": 7.6159,
        "CZK": 26.293,
        "DKK": 7.4378,
        "GBP": 0.88143,
        "HKD": 8.7015,
        "HRK": 7.4175,
        "HUF": 309.13,
        "IDR": 14830.34,
        "ILS": 3.9482,
        "INR": 71.9705,
        "JPY": 124.25,
        "KRW": 1271.75,
        "MXN": 20.2098,
        "MYR": 4.785,
        "NOK": 9.493,
        "NZD": 1.5414,
        "PHP": 55.902,
        "PLN": 4.2306,
        "RON": 4.5988,
        "RUB": 66.2746,
        "SEK": 9.7575,
        "SGD": 1.5482,
        "THB": 37.919,
        "TRY": 3.945,
        "USD": 1.1156,
        "ZAR": 14.6166
    }
}
