{
    "base": "EUR",
    "date": "2017-02-14",
    "rates": {
        "AUD": 1.3813,
        "BGN": 1.9558,
        "BRL": 3.2881,
        "CAD": 1.3842,
        "CHF": 1.0659,
        "CNY": 7.2902,
        "CZK": 27.021,
        "DKK": 7.4359,
        "GBP": 0.85098,
        "HKD": 8.2422,
        "HRK": 7.4537,
        "HUF": 308.13,
        "IDR": 14138.08,
        "ILS": 3.9783,
        "INR": 70.9755,
        "JPY": 120.43,
        "KRW": 1207.63,
        "MXN": 21.4981,
        "MYR": 4.7263,
        "NOK": 8.879,
        "NZD": 1.478,
        "PHP": 52.952,
        "PLN": 4.3012,
        "RON": 4.5051,
        "RUB": 60.9409,
        "SEK": 9.4653,
        "SGD": 1.5044,
        "THB": 37.154,
        "TRY": 3.878,
        "USD": 1.0623,
        "ZAR": 13.914
    }
}
