{
    "base": "EUR",
    "date": "2018-12-24",
    "rates": {
        "AUD": 1.6186,
        "BGN": 1.9558,
        "BRL": 4.4537,
        "CAD": 1.5506,
        "CHF": 1.1312,
        "CNY": 7.873,
        "CZK": 25.916,
        "DKK": 7.4663,
        "GBP": 0.90038,
        "HKD": 8.9359,
        "HRK": 7.422,
        "HUF": 321.0,
        "IDR": 16642.56,
        "ILS": 4.315,
        "INR": 80.019,
        "ISK": 133.2,
        "JPY": 126.47,
        "KRW": 1283.61,
        "MXN": 22.6549,
        "MYR": 4.7611,
        "NOK": 10.0025,
        "NZD": 1.6974,
        "PHP": 60.417,
        "PLN": 4.2848,
        "RON": 4.6428,
        "RUB": 78.096,
        "SEK": 10.3428,
        "SGD": 1.5655,
        "THB": 37.162,
        "TRY": 6.048,
        "USD": 1.1408,
        "ZAR": 16.6876
    }
}
