{
    "base": "EUR",
    "date": "2018-04-25",
    "rates": {
        "AUD": 1.6118,
        "BGN": 1.9558,
        "BRL": 4.2705,
        "CAD": 1.5704,
        "CHF": 1.1986,
        "CNY": 7.7048,
        "CZK": 25.466,
        "DKK": 7.4489,
        "GBP": 0.8738,
        "HKD": 9.5625,
        "HRK": 7.4185,
        "HUF": 313.2,
        "IDR": 16961.52,
        "ILS": 4.3776,
        "INR": 81.6095,
        "ISK": 123.0,
        "JPY": 133.03,
        "KRW": 1320.61,
        "MXN": 23.2194,
        "MYR": 4.7712,
        "NOK": 9.705,
        "NZD": 1.7232,
        "PHP": 63.773,
        "PLN": 4.2241,
        "RON": 4.6453,
        "RUB": 75.7073,
        "SEK": 10.422,
        "SGD": 1.6199,
        "THB": 38.486,
        "TRY": 5.0008,
        "USD": 1.2185,
        "ZAR": 15.2415
    }
}
