{
    "base": "EUR",
    "date": "2019-05-28",
    "rates": {
        "AUD": 1.6162,
        "BGN": 1.9558,
        "BRL": 4.5305,
        "CAD": 1.5071,
        "CHF": 1.1254,
        "CNY": 7.7345,
        "CZK": 25.843,
        "DKK": 7.4689,
        "GBP": 0.88373,
        "HKD": 8.7839,
        "HRK": 7.4255,
        "HUF": 326.6,
        "IDR": 16088.5,
        "ILS": 4.0445,
        "INR": 77.9025,
        "ISK": 138.7,
        "JPY": 122.45,
        "KRW": 1329.89,
        "MXN": 21.3797,
        "MYR": 4.6878,
        "NOK": 9.7165,
        "NZD": 1.7088,
        "PHP": 58.489,
        "PLN": 4.2951,
        "RON": 4.7623,
        "RUB": 72.2891,
        "SEK": 10.6865,
        "SGD": 1.542,
        "THB": 35.602,
        "TRY": 6.753,
        "USD": 1.1192,
        "ZAR": 16.3494
    }
}
